cozepy/__init__.py
cozepy/config.py
cozepy/coze.py
cozepy/exception.py
cozepy/log.py
cozepy/model.py
cozepy/py.typed
cozepy/request.py
cozepy/util.py
cozepy/version.py
cozepy/audio/__init__.py
cozepy/audio/rooms/__init__.py
cozepy/audio/speech/__init__.py
cozepy/audio/voices/__init__.py
cozepy/auth/__init__.py
cozepy/bots/__init__.py
cozepy/chat/__init__.py
cozepy/chat/message/__init__.py
cozepy/conversations/__init__.py
cozepy/conversations/message/__init__.py
cozepy/files/__init__.py
cozepy/knowledge/__init__.py
cozepy/knowledge/documents/__init__.py
cozepy/workflows/__init__.py
cozepy/workflows/runs/__init__.py
cozepy/workflows/runs/run_histories/__init__.py
cozepy/workspaces/__init__.py
tests/__init__.py
tests/config.py
tests/test_audio_rooms.py
tests/test_audio_speech.py
tests/test_audio_voices.py
tests/test_auth.py
tests/test_bot.py
tests/test_chat.py
tests/test_chat_message.py
tests/test_conversation.py
tests/test_conversation_message.py
tests/test_exception.py
tests/test_file.py
tests/test_knowledge_documents.py
tests/test_log.py
tests/test_model.py
tests/test_request.py
tests/test_util.py
tests/test_version.py
tests/test_workflow.py
tests/test_workspace.py
cozepy_pydantic1-0.6.2.dist-info/LICENSE
cozepy_pydantic1-0.6.2.dist-info/METADATA
cozepy_pydantic1-0.6.2.dist-info/WHEEL
cozepy_pydantic1-0.6.2.dist-info/top_level.txt
cozepy_pydantic1-0.6.2.dist-info/RECORD
